omg/__init__.py
omg/__main__.py
omg/colored.py
omg/pretty_print_exc.py
omg/print.py
omg-1.3.9.dist-info/METADATA
omg-1.3.9.dist-info/WHEEL
omg-1.3.9.dist-info/entry_points.txt
omg-1.3.9.dist-info/licenses/LICENSE
omg-1.3.9.dist-info/RECORD
