Metadata-Version: 2.4
Name: omg
Version: 1.3.9
Summary: A Python CLI replacement with live reload capabilities, enabling fast restarts by reloading only user modules. Ideal for iterative development and prototyping.
Project-URL: Repository, https://github.com/Reddan/omg.git
Author: Hampus Hallman
License: Copyright 2019-2025 Hampus Hallman
License-File: LICENSE
Classifier: Programming Language :: Python :: 3.10
Classifier: Programming Language :: Python :: 3.11
Classifier: Programming Language :: Python :: 3.12
Classifier: Programming Language :: Python :: 3.13
Requires-Python: >=3.10
Requires-Dist: watchdog
